[{"id":"f3db64f0.567f58","type":"tab","label":"Flow 1"},{"id":"ecbe37e0.b67f88","type":"tab","label":"Flow 2"},{"id":"1ff93311.c1f70d","type":"mqtt-broker","z":"","broker":"192.168.178.44","port":"1883","clientid":"","usetls":false,"compatmode":true,"keepalive":"60","cleansession":true,"willTopic":"","willQos":"0","willPayload":"","birthTopic":"","birthQos":"0","birthPayload":""},{"id":"6c9df452.a11a2c","type":"http in","z":"f3db64f0.567f58","name":"","url":"/in","method":"get","upload":false,"swaggerDoc":"","x":205.10000610351562,"y":135,"wires":[["89e549bd.bc3978","c32ccb37.dbb978"]]},{"id":"89e549bd.bc3978","type":"mqtt out","z":"f3db64f0.567f58","name":"","topic":"fromnodered","qos":"","retain":"","broker":"1ff93311.c1f70d","x":529.1000366210938,"y":212,"wires":[]},{"id":"c32ccb37.dbb978","type":"http response","z":"f3db64f0.567f58","name":"","statusCode":"","headers":{},"x":213.10000610351562,"y":276,"wires":[]},{"id":"dd6c0cdf.4ff54","type":"debug","z":"f3db64f0.567f58","name":"","active":true,"console":"false","complete":"false","x":524.1000366210938,"y":501,"wires":[]},{"id":"274e7569.cb43aa","type":"mqtt in","z":"f3db64f0.567f58","name":"","topic":"fromnodered","qos":"2","broker":"1ff93311.c1f70d","x":253.10000610351562,"y":501,"wires":[["dd6c0cdf.4ff54"]]}]